pyphorus/__init__.py
pyphorus/devices.py
pyphorus/pyphorus.py
pyphorus/scanners/__init__.py
pyphorus/scanners/port_scanner.py
pyphorus/scanners/upnp_scanner.py
pyphorus/utils/__init__.py
pyphorus/utils/utils.py
pyphorus-0.0.3.dist-info/LICENSE.md
pyphorus-0.0.3.dist-info/METADATA
pyphorus-0.0.3.dist-info/WHEEL
pyphorus-0.0.3.dist-info/top_level.txt
pyphorus-0.0.3.dist-info/RECORD
