Metadata-Version: 2.1
Name: pyphorus
Version: 0.0.3
Summary: A network utility library written in Python 3
Home-page: https://github.com/Oleaintueri/pyphorus
Author: Benehiko
Author-email: alano@oleaintueri.com
License: GPL-3.0
Platform: UNKNOWN
Requires-Python: >=3.6.0
Requires-Dist: requests (==2.25.1)
Requires-Dist: nose (==1.3.7)
Requires-Dist: aiohttp (==3.7.3)
Requires-Dist: ssdpy (==0.4.1)
Requires-Dist: defusedxml (==0.6.0)
Requires-Dist: setuptools (==51.1.0)
